bestconfig/__init__.py
bestconfig/adapters.py
bestconfig/config.py
bestconfig/config_provider.py
bestconfig/converters.py
bestconfig/file_parsers.py
bestconfig/source.py
bestconfig/source_resolver.py
bestconfig-1.3.6.dist-info/METADATA
bestconfig-1.3.6.dist-info/WHEEL
bestconfig-1.3.6.dist-info/top_level.txt
bestconfig-1.3.6.dist-info/RECORD
