Metadata-Version: 2.1
Name: bestconfig
Version: 1.3.6
Summary: Setup your project config easily
Home-page: https://github.com/fivol/bestconfig
Author: Boris Bondarenko
Author-email: borisoffficial@gmail.com
License: MIT
